sf_price_fetcher/__init__.py
sf_price_fetcher/__main__.py
sf_price_fetcher/lookups.py
sf_price_fetcher-0.1.0.dist-info/LICENSE
sf_price_fetcher-0.1.0.dist-info/METADATA
sf_price_fetcher-0.1.0.dist-info/WHEEL
sf_price_fetcher-0.1.0.dist-info/top_level.txt
sf_price_fetcher-0.1.0.dist-info/RECORD
