Metadata-Version: 2.1
Name: sf-price-fetcher
Version: 0.1.0
Summary: Fetches MTG card price info from scryfall.com
Home-page: https://github.com/intuited/sf_price_fetcher
Author: Ted Tibbetts
Author-email: ted@circulated.ca
License: UNKNOWN
Platform: UNKNOWN
Classifier: Programming Language :: Python :: 3
Classifier: License :: OSI Approved :: MIT License
Classifier: Operating System :: OS Independent
License-File: LICENSE
Requires-Dist: requests
Requires-Dist: pypaxtor
